README.html
ez_setup.py
lgpl.txt
setup.cfg
setup.py
NoseXUnit.egg-info/PKG-INFO
NoseXUnit.egg-info/SOURCES.txt
NoseXUnit.egg-info/dependency_links.txt
NoseXUnit.egg-info/entry_points.txt
NoseXUnit.egg-info/requires.txt
NoseXUnit.egg-info/top_level.txt
NoseXUnit.egg-info/zip-safe
nosexunit/__init__.py
nosexunit/blank.png
nosexunit/const.py
nosexunit/core.py
nosexunit/cyclo.py
nosexunit/excepts.py
nosexunit/nosexunit.css
nosexunit/nosexunit.js
nosexunit/plugin.py
nosexunit/tools.py
nosexunit/audit/__init__.py
nosexunit/audit/abstract.html
nosexunit/audit/code.html
nosexunit/audit/detail.html
nosexunit/audit/error.html
nosexunit/audit/index.html
nosexunit/audit/listing.html
nosexunit/cover/__init__.py
nosexunit/cover/abstract.html
nosexunit/cover/clover.xml
nosexunit/cover/cobertura.xml
nosexunit/cover/code.html
nosexunit/cover/error.html
nosexunit/cover/index.html
nosexunit/cover/listing.html
test_NoseXUnit/__init__.py
test_NoseXUnit/test.properties.model
test_NoseXUnit/plugin/__init__.py
test_NoseXUnit/plugin/test_audit/__init__.py
test_NoseXUnit/plugin/test_audit/test_audit_package.py
test_NoseXUnit/plugin/test_core/__init__.py
test_NoseXUnit/plugin/test_core/test_file_name.py
test_NoseXUnit/plugin/test_core/test_yield_error.py
test_NoseXUnit/plugin/test_cover/__init__.py
test_NoseXUnit/plugin/test_cover/test_cover_all.py
test_NoseXUnit/plugin/test_cover/test_ro_src.py
test_NoseXUnit/unit/__init__.py
test_NoseXUnit/unit/test_audit/__init__.py
test_NoseXUnit/unit/test_audit/test_check_pylintrc.py
test_NoseXUnit/unit/test_core/__init__.py
test_NoseXUnit/unit/test_core/test_std_recorder.py
test_NoseXUnit/unit/test_core/test_unicode.py
test_NoseXUnit/unit/test_cover/__init__.py
test_NoseXUnit/unit/test_cover/test_parse.py
test_NoseXUnit/unit/test_plugin/__init__.py
test_NoseXUnit/unit/test_tools/__init__.py
test_NoseXUnit/unit/test_tools/test_clean.py
test_NoseXUnit/unit/test_tools/test_create.py
test_NoseXUnit/unit/test_tools/test_package.py
test_NoseXUnit/unit/test_tools/test_packages.py
test_NoseXUnit/unit/test_tools/test_save_load.py
test_NoseXUnit/unit/test_tools/test_split.py