Metadata-Version: 1.0
Name: NoseXUnit
Version: 0.3.3
Summary: XML Output plugin for Nose
Home-page: http://nosexunit.sourceforge.net
Author: Olivier Mansion
Author-email: nosexunit@gmail.com
License: GNU Library or Lesser General Public License (LGPL)
Platform: UNKNOWN
Classifier: Development Status :: 5 - Production/Stable
Classifier: Environment :: Plugins
Classifier: Intended Audience :: Developers
Classifier: License :: Public Domain
Classifier: Natural Language :: English
Classifier: Operating System :: POSIX
Classifier: Programming Language :: Python
Classifier: Topic :: Software Development :: Testing
